mabble/__init__.py
mabble-0.0.1.dist-info/METADATA
mabble-0.0.1.dist-info/WHEEL
mabble-0.0.1.dist-info/top_level.txt
mabble-0.0.1.dist-info/RECORD
