Metadata-Version: 2.4
Name: mabble
Version: 0.0.1
Summary: mabble.
Author-email: Nathan Fulton <nathan@ibm.com>
Classifier: Programming Language :: Python :: 3
Classifier: Operating System :: OS Independent
Requires-Python: >=3.12
